itaxotools_mafftpy-0.3.0.dist-info/RECORD
itaxotools_mafftpy-0.3.0.dist-info/WHEEL
itaxotools_mafftpy-0.3.0.dist-info/entry_points.txt
itaxotools_mafftpy-0.3.0.dist-info/METADATA
itaxotools_mafftpy-0.3.0.dist-info/licenses/LICENSE.txt
itaxotools/_mafft.cpython-311-darwin.so
itaxotools/mafftpy/__init__.py
itaxotools/mafftpy/core.py
itaxotools/mafftpy/__main__.py
