Metadata-Version: 2.2
Name: itaxotools-mafftpy
Version: 0.3.0
Summary: A Python wrapper for MAFFT
Author-Email: Patmanidis Stefanos <stefanpatman91@gmail.com>
Classifier: License :: OSI Approved :: GNU General Public License v3 or later (GPLv3+)
Classifier: Development Status :: 5 - Production/Stable
Classifier: Programming Language :: Python
Classifier: Programming Language :: Python :: 3.10
Classifier: Programming Language :: Python :: 3.11
Classifier: Programming Language :: Python :: 3.12
Classifier: Programming Language :: Python :: Implementation :: CPython
Project-URL: Homepage, https://itaxotools.org/
Project-URL: Source, https://github.com/iTaxoTools/MAFFTpy
Requires-Python: <4,>=3.10.2
Requires-Dist: itaxotools-common>=0.3.3
Provides-Extra: dev
Requires-Dist: setuptools-scm; extra == "dev"
Requires-Dist: cibuildwheel; extra == "dev"
Requires-Dist: delocate; extra == "dev"
Requires-Dist: pre-commit; extra == "dev"
Requires-Dist: ruff; extra == "dev"
Requires-Dist: pytest; extra == "dev"
